FPGA_Design/Neuron_Design/include.v
`define pretrained
`define numLayers 5
`define dataWidth 16
`define numNeuronLayer1 30
`define numWeightLayer1 784
`define Layer1ActType "sigmoid"
`define numNeuronLayer2 30
`define numWeightLayer2 30
`define Layer2ActType "sigmoid"
`define numNeuronLayer3 10
`define numWeightLayer3 30
`define Layer3ActType "sigmoid"
`define numNeuronLayer4 10
`define numWeightLayer4 10
`define Layer4ActType "sigmoid"
`define numNeuronLayer5 10
`define numWeightLayer5 10
`define Layer5ActType "hardmax"
`define sigmoidSize 10
`define weightIntWidth 2

FPGA_Design/Neuron design/ReLU.v
`timescale 1ns/1ps

module ReLU #(parameter dataWidth=16, weightIntWidth=1)(
    input clk,
    input [2*dataWidth-1:0] x,
    output reg [dataWidth-1:0] out
);
    always @(posedge clk) begin
        if(x[2*dataWidth-1])
            out <= 0;
        else
            out <= x[2*dataWidth-2-:dataWidth];
    end
endmodule

FPGA_Design/Neuron_Design/Weight_Memory.v
`timescale 1ns / 1ps
`include "include.v"

module Weight_Memory #(parameter numWeight = 3, neuronNo=5,layerNo=1,addressWidth=10,dataWidth=16,weightFile="w_1_15.mif") 
    ( 
    input clk,
    input wen,
    input ren,
    input [addressWidth-1:0] wadd,
    input [addressWidth:0] radd,
    input [dataWidth-1:0] win,
    output reg [dataWidth-1:0] wout);
    
    reg [dataWidth-1:0] mem [numWeight-1:0];

    `ifdef pretrained //acts as rom because it is predefined, otherwise it would act as a RAM, so ifdef makes sure its defined
        initial
		begin
	        $readmemb(weightFile, mem);// transfers weights to mem
	    end
	`else
		always @(posedge clk)//this stores it as a normal RAM
		begin
			if (wen)
			begin
				mem[wadd] <= win;// writed the weight value into the array memory stored at wadd
			end
		end 
    `endif
    
    always @(posedge clk)
    begin
        if (ren && radd < numWeight)
        begin
            wout <= mem[radd];
        end
    end
endmodule

FPGA_Design/Neuron_Design/neuron.v
`timescale 1ns / 1ps

`include "include.v"

module neuron # (parameter layerNo=0,neuronNo=0,numWeight=784,dataWidth=16, sigmoidSize=5, weightIntWidth=1,actType="relu",biasFile="",weightFile="")(
    input clk,
    input rst,
    input [dataWidth-1:0] myinput,
    input myinputValid,
    input weightValid, 
    input biasValid, 
    input [31:0] weightValue, 
    input [31:0] biasValue,
    input [31:0] config_neuron_num,
    input [31:0] config_layer_num, 
    output [dataWidth-1:0] out, 
    output reg outvalid
);
    
    parameter addressWidth = $clog2(numWeight);
    
    reg wen;
    wire ren;
    reg [addressWidth-1:0] w_addr;
    reg [addressWidth:0]   r_addr;//read address has to reach until numWeight hence width is 1 bit more
    reg [dataWidth-1:0]  w_in;
    wire [dataWidth-1:0] w_out;
    reg [2*dataWidth-1:0]  mul; 
    reg [2*dataWidth-1:0]  sum;
    reg [2*dataWidth-1:0]  bias;
    reg [31:0]    biasReg[0:0];
    reg         weight_valid;
    reg         mult_valid;
    wire        mux_valid;
    reg         sigValid; 
    wire [2*dataWidth:0] comboAdd;
    wire [2*dataWidth:0] BiasAdd;
    reg  [dataWidth-1:0] myinputd;
    reg muxValid_d;
    reg muxValid_f;
    reg addr=0;
   //Loading weight values into the memory
    always @(posedge clk)
    begin
        if(rst)
        begin
            w_addr <= {addressWidth{1'b1}}; //means replicate 1 bit 1 to the amount thats listed in address width which is found using log in the parameter function above
            wen <=0;
        end
        else if(weightValid & (config_layer_num==layerNo) & (config_neuron_num==neuronNo))// only happens if the conditions are met and weight valid is high
        begin
            w_in <= weightValue; 
            w_addr <= w_addr + 1;
            wen <= 1; // adds weight value to weight input and then changes the address to the next bit, it then puts write enable to 1, if the above conditions are not met wen = 0
        end
        else
            wen <= 0;
    end

    assign mux_valid = mult_valid;
    assign comboAdd = mul + sum;
    assign BiasAdd = bias + sum;
    assign ren = myinputValid;
    
    `ifdef pretrained
        initial
        begin
            $readmemb(biasFile,biasReg);
        end
        always @(posedge clk)
        begin
            bias <= {biasReg[addr][dataWidth-1:0],{dataWidth{1'b0}}};
        end
    `else
        always @(posedge clk)
        begin
            if(biasValid & (config_layer_num==layerNo) & (config_neuron_num==neuronNo))
            begin
                bias <= {biasValue[dataWidth-1:0],{dataWidth{1'b0}}};
            end
        end
    `endif
    
    
    always @(posedge clk)
    begin
        if(rst|outvalid)
            r_addr <= 0;
        else if(myinputValid)
            r_addr <= r_addr + 1;
    end
    
    always @(posedge clk)
    begin
        mul  <= $signed(myinputd) * $signed(w_out);
    end
    
    
    always @(posedge clk)
    begin
        if(rst|outvalid)
            sum <= 0;
        else if((r_addr == numWeight) & muxValid_f)
        begin
            if(!bias[2*dataWidth-1] &!sum[2*dataWidth-1] & BiasAdd[2*dataWidth-1]) //If bias and sum are positive and after adding bias to sum, if sign bit becomes 1, set it to maximum value
            begin
                sum[2*dataWidth-1] <= 1'b0;
                sum[2*dataWidth-2:0] <= {2*dataWidth-1{1'b1}};
            end
            else if(bias[2*dataWidth-1] & sum[2*dataWidth-1] &  !BiasAdd[2*dataWidth-1]) //If bias and sum are negative and after addition if sign bit is 0, set it to minimium value 
            begin
                sum[2*dataWidth-1] <= 1'b1;
                sum[2*dataWidth-2:0] <= {2*dataWidth-1{1'b0}};
            end
            else
                sum <= BiasAdd; 
        end
        else if(mux_valid)
        begin
            if(!mul[2*dataWidth-1] & !sum[2*dataWidth-1] & comboAdd[2*dataWidth-1])
            begin
                sum[2*dataWidth-1] <= 1'b0;
                sum[2*dataWidth-2:0] <= {2*dataWidth-1{1'b1}};
            end
            else if(mul[2*dataWidth-1] & sum[2*dataWidth-1] & !comboAdd[2*dataWidth-1])
            begin
                sum[2*dataWidth-1] <= 1'b1;
                sum[2*dataWidth-2:0] <= {2*dataWidth-1{1'b0}};
            end
            else
                sum <= comboAdd; 
        end
    end
    
    always @(posedge clk)
    begin
        myinputd <= myinput; //my inputd because it is delayed by 1 clock, so have to do this to have them equal to each other
        weight_valid <= myinputValid;
        mult_valid <= weight_valid;
        sigValid <= ((r_addr == numWeight) & muxValid_f) ? 1'b1 : 1'b0;
        outvalid <= sigValid;
        muxValid_d <= mux_valid;
        muxValid_f <= !mux_valid & muxValid_d;
    end
    
    
    //Instantiation of Memory for Weights
    Weight_Memory #(.numWeight(numWeight),.neuronNo(neuronNo),.layerNo(layerNo),.addressWidth(addressWidth),.dataWidth(dataWidth),.weightFile(weightFile)) WM(
        .clk(clk),
        .wen(wen),
        .ren(ren),
        .wadd(w_addr),
        .radd(r_addr),
        .win(w_in),
        .wout(w_out)
    );
    
    generate
        if(actType == "sigmoid")
        begin:siginst
        //Instantiation of ROM for sigmoid
            Sig_ROM #(.inWidth(sigmoidSize),.dataWidth(dataWidth)) s1(
            .clk(clk),
            .x(sum[2*dataWidth-1-:sigmoidSize]),
            .out(out)
        );
        end
        else
        begin:ReLUinst
            ReLU #(.dataWidth(dataWidth),.weightIntWidth(weightIntWidth)) s1 (
            .clk(clk),
            .x(sum),
            .out(out)
        );
        end
    endgenerate

    `ifdef DEBUG
    always @(posedge clk)
begin
    if(rst|outvalid)
        r_addr <= 0;
    else if(myinputValid | weight_valid)
        r_addr <= r_addr + 1;
end
    `endif
endmodule

FPGA_Design/Neuron_Design/neuron_tb.v
`timescale 1ns/1ps
`include "include.v"

module neuron_tb;

    parameter dataWidth = 16;
    parameter numWeight = 4;
    parameter sigmoidSize = 10;

    reg clk, rst;
    reg [dataWidth-1:0] myinput;
    reg myinputValid;
    reg weightValid, biasValid;
    reg [31:0] weightValue, biasValue;
    reg [31:0] config_neuron_num;
    reg [31:0] config_layer_num;
    wire [dataWidth-1:0] out;
    wire outvalid;

    always #5 clk = ~clk;

    neuron #(
        .layerNo(0),
        .neuronNo(0),
        .numWeight(numWeight),
        .dataWidth(dataWidth),
        .sigmoidSize(sigmoidSize),
        .weightIntWidth(2),
        .actType("relu"),
        .biasFile("b_1_15.mif"),
        .weightFile("w_1_15.mif")
    ) dut (
        .clk(clk),
        .rst(rst),
        .myinput(myinput),
        .myinputValid(myinputValid),
        .weightValid(weightValid),
        .biasValid(biasValid),
        .weightValue(weightValue),
        .biasValue(biasValue),
        .config_neuron_num(config_neuron_num),
        .config_layer_num(config_layer_num),
        .out(out),
        .outvalid(outvalid)
    );

    initial begin
        $dumpfile("neuron_tb.vcd");
        $dumpvars(0, neuron_tb);
    end

    integer i;
    initial begin
        clk = 0; rst = 1;
        myinput = 0; myinputValid = 0;
        weightValid = 0; biasValid = 0;
        weightValue = 0; biasValue = 0;
        config_neuron_num = 0;
        config_layer_num = 0;

        repeat(4) @(posedge clk);
        rst = 0;
        repeat(2) @(posedge clk);

        // feed 4 inputs
        for(i = 0; i < numWeight; i = i+1) begin
            myinput = i * 100;
            myinputValid = 1;
            @(posedge clk);
        end
        myinputValid = 0;

        // wait for output
        repeat(20) @(posedge clk);

        if(outvalid)
            $display("OUTPUT VALID: out = %b (%0d)", out, $signed(out));
        else
            $display("outvalid never went high");

        $finish;
    end

endmodule

FPGA_Design/Neuron_Design/neuron_tb.vcd
$date
	Sat Aug 29 17:02:42 2026
$end
$version
	Icarus Verilog
$end
$timescale
	1ps
$end
$scope module neuron_tb $end
$var wire 1 ! outvalid $end
$var wire 16 " out [15:0] $end
$var parameter 32 # dataWidth $end
$var parameter 32 $ numWeight $end
$var parameter 32 % sigmoidSize $end
$var reg 1 & biasValid $end
$var reg 32 ' biasValue [31:0] $end
$var reg 1 ( clk $end
$var reg 32 ) config_layer_num [31:0] $end
$var reg 32 * config_neuron_num [31:0] $end
$var reg 16 + myinput [15:0] $end
$var reg 1 , myinputValid $end
$var reg 1 - rst $end
$var reg 1 . weightValid $end
$var reg 32 / weightValue [31:0] $end
$var integer 32 0 i [31:0] $end
$scope module dut $end
$var wire 1 & biasValid $end
$var wire 32 1 biasValue [31:0] $end
$var wire 1 ( clk $end
$var wire 32 2 config_layer_num [31:0] $end
$var wire 32 3 config_neuron_num [31:0] $end
$var wire 1 4 mux_valid $end
$var wire 16 5 myinput [15:0] $end
$var wire 1 , myinputValid $end
$var wire 1 6 ren $end
$var wire 1 - rst $end
$var wire 1 . weightValid $end
$var wire 32 7 weightValue [31:0] $end
$var wire 16 8 w_out [15:0] $end
$var wire 16 9 out [15:0] $end
$var wire 33 : comboAdd [32:0] $end
$var wire 33 ; BiasAdd [32:0] $end
$var parameter 32 < actType $end
$var parameter 32 = addressWidth $end
$var parameter 80 > biasFile $end
$var parameter 32 ? dataWidth $end
$var parameter 32 @ layerNo $end
$var parameter 32 A neuronNo $end
$var parameter 32 B numWeight $end
$var parameter 32 C sigmoidSize $end
$var parameter 80 D weightFile $end
$var parameter 32 E weightIntWidth $end
$var reg 1 F addr $end
$var reg 32 G bias [31:0] $end
$var reg 32 H mul [31:0] $end
$var reg 1 I mult_valid $end
$var reg 1 J muxValid_d $end
$var reg 1 K muxValid_f $end
$var reg 16 L myinputd [15:0] $end
$var reg 1 ! outvalid $end
$var reg 3 M r_addr [2:0] $end
$var reg 1 N sigValid $end
$var reg 32 O sum [31:0] $end
$var reg 2 P w_addr [1:0] $end
$var reg 16 Q w_in [15:0] $end
$var reg 1 R weight_valid $end
$var reg 1 S wen $end
$scope begin ReLUinst $end
$scope module s1 $end
$var wire 1 ( clk $end
$var wire 32 T x [31:0] $end
$var parameter 32 U dataWidth $end
$var parameter 32 V weightIntWidth $end
$var reg 16 W out [15:0] $end
$upscope $end
$upscope $end
$scope module WM $end
$var wire 1 ( clk $end
$var wire 2 X radd [1:0] $end
$var wire 1 6 ren $end
$var wire 2 Y wadd [1:0] $end
$var wire 1 S wen $end
$var wire 16 Z win [15:0] $end
$var parameter 32 [ addressWidth $end
$var parameter 32 \ dataWidth $end
$var parameter 32 ] layerNo $end
$var parameter 32 ^ neuronNo $end
$var parameter 32 _ numWeight $end
$var parameter 80 ` weightFile $end
$var reg 16 a wout [15:0] $end
$upscope $end
$upscope $end
$upscope $end
$enddefinitions $end
$comment Show the parameter values. $end
$dumpall
b1110111010111110011000101011111001100010011010100101110011011010110100101100110 `
b100 _
b0 ^
b0 ]
b10000 \
b10 [
b1 V
b10000 U
b1 E
b1110111010111110011000101011111001100010011010100101110011011010110100101100110 D
b101 C
b100 B
b0 A
b0 @
b10000 ?
b1100010010111110011000101011111001100010011010100101110011011010110100101100110 >
b10 =
b1110010011001010110110001110101 <
b101 %
b100 $
b10000 #
$end
#0
$dumpvars
bx a
bx Z
bx Y
bx X
bx W
bx T
xS
xR
bx Q
bx P
bx O
xN
bx M
bx L
xK
xJ
xI
bx H
bx G
0F
bx ;
bx :
bx 9
bx 8
b0 7
06
b0 5
x4
b0 3
b0 2
b0 1
bx 0
b0 /
0.
1-
0,
b0 +
b0 *
b0 )
0(
b0 '
0&
bx "
x!
$end
#5000
b101010001000000000000000000000 ;
b0 X
0S
b11 P
b11 Y
b101010001000000000000000000000 G
b0 M
b0 O
b0 T
0R
b0 L
1(
#10000
0(
#15000
0N
04
0I
b0 "
b0 9
b0 W
1(
#20000
0(
#25000
0J
0!
1(
#30000
0(
#35000
0K
0-
1(
#40000
0(
#45000
1(
#50000
0(
#55000
16
1,
b0 0
1(
#60000
0(
#65000
b1 X
b11100111011 8
b11100111011 a
b1 M
1R
b1100100 L
b1100100 +
b1100100 5
b1 0
1(
#70000
0(
#75000
b101101001100001100 :
b10 X
14
1I
b101101001100001100 H
b10 M
b1101101011110101 8
b1101101011110101 a
b11001000 +
b11001000 5
b10 0
1(
#80000
0(
#85000
b11 X
b11111111111101000101101011000000 :
b101010001000101101001100001100 ;
b1011001101010 8
b1011001101010 a
b11 M
b11111111111100011000011110110100 H
b101101001100001100 O
b101101001100001100 T
1J
b100101100 L
b100101100 +
b100101100 5
b11 0
1(
#90000
0(
#95000
b100101010000101000101101011000000 ;
b100000000000011101001111011111000 :
b0 X
b11111111111101000101101011000000 O
b11111111111101000101101011000000 T
b110100100010000111000 H
b100 M
b1111011100110000 8
b1111011100110000 a
b101 "
b101 9
b101 W
06
0,
b100 0
1(
#100000
0(
#105000
b100000000000001000100101100111000 :
b101010001011101001111011111000 ;
b0 "
b0 9
b0 W
b11111111111101011010110001000000 H
b11101001111011111000 O
b11101001111011111000 T
0R
1(
#110000
0(
#115000
b11111111111110011111011101111000 :
b101010001001000100101100111000 ;
04
0I
b1000100101100111000 O
b1000100101100111000 T
b11101 "
b11101 9
b11101 W
1(
#120000
0(
#125000
b1000 "
b1000 9
b1000 W
1K
0J
1(
#130000
0(
#135000
b100101010000110011111011101111000 :
b1010100010001000100101100111000 ;
0K
1N
b101010001001000100101100111000 O
b101010001001000100101100111000 T
1(
#140000
0(
#145000
b101010001001000 "
b101010001001000 9
b101010001001000 W
1!
0N
1(
#150000
0(
#155000
b11111111111101011010110001000000 :
b101010001000000000000000000000 ;
0!
b0 O
b0 T
b0 M
1(
#160000
0(
#165000
b0 "
b0 9
b0 W
1(
